{
  "department_id": 402,
  "department_name": "Pantry Staples",
  "season": {
    "name": "Fall/Holiday",
    "preseason_pct": 20.0,
    "inseason_pct": 70.0,
    "markdown_pct": 10.0
  },
  "sku_clusters": [
    {
      "cluster_id": "PA_A_001",
      "segment": "A",
      "item_name": "Pantry Staples - A Item 1",
      "demand_mean": 141553.0,
      "demand_std": 21233.0,
      "unit_cost": 110.48,
      "margin_pct": 42.8,
      "pog_capacity": 53700.0
    },
    {
      "cluster_id": "PA_A_002",
      "segment": "A",
      "item_name": "Pantry Staples - A Item 2",
      "demand_mean": 109046.0,
      "demand_std": 16357.0,
      "unit_cost": 115.4,
      "margin_pct": 45.1,
      "pog_capacity": 54616.0
    },
    {
      "cluster_id": "PA_B_003",
      "segment": "B",
      "item_name": "Pantry Staples - B Item 3",
      "demand_mean": 51314.0,
      "demand_std": 10263.0,
      "unit_cost": 50.9,
      "margin_pct": 48.8,
      "pog_capacity": 39978.0
    },
    {
      "cluster_id": "PA_B_004",
      "segment": "B",
      "item_name": "Pantry Staples - B Item 4",
      "demand_mean": 59586.0,
      "demand_std": 11917.0,
      "unit_cost": 40.4,
      "margin_pct": 48.1,
      "pog_capacity": 26902.0
    },
    {
      "cluster_id": "PA_C_005",
      "segment": "C",
      "item_name": "Pantry Staples - C Item 5",
      "demand_mean": 28798.0,
      "demand_std": 8639.0,
      "unit_cost": 28.59,
      "margin_pct": 56.8,
      "pog_capacity": 14827.0
    },
    {
      "cluster_id": "PA_C_006",
      "segment": "C",
      "item_name": "Pantry Staples - C Item 6",
      "demand_mean": 19716.0,
      "demand_std": 5915.0,
      "unit_cost": 32.44,
      "margin_pct": 58.6,
      "pog_capacity": 13503.0
    },
    {
      "cluster_id": "PA_R_007",
      "segment": "R",
      "item_name": "Pantry Staples - R Item 7",
      "demand_mean": 52144.0,
      "demand_std": 6257.0,
      "unit_cost": 24.8,
      "margin_pct": 49.9,
      "pog_capacity": 20578.0
    },
    {
      "cluster_id": "PA_R_008",
      "segment": "R",
      "item_name": "Pantry Staples - R Item 8",
      "demand_mean": 53399.0,
      "demand_std": 6408.0,
      "unit_cost": 62.47,
      "margin_pct": 48.3,
      "pog_capacity": 22311.0
    }
  ],
  "total_demand_value": 39333584.0,
  "total_budget_needed": 46898504.0
}