{
  "department_id": 902,
  "department_name": "Cat Supplies",
  "season": {
    "name": "Fall/Holiday",
    "preseason_pct": 25.0,
    "inseason_pct": 65.0,
    "markdown_pct": 10.0
  },
  "sku_clusters": [
    {
      "cluster_id": "CA_A_001",
      "segment": "A",
      "item_name": "Cat Supplies - A Item 1",
      "demand_mean": 141130.0,
      "demand_std": 21169.0,
      "unit_cost": 73.34,
      "margin_pct": 45.8,
      "pog_capacity": 34243.0
    },
    {
      "cluster_id": "CA_A_002",
      "segment": "A",
      "item_name": "Cat Supplies - A Item 2",
      "demand_mean": 104487.0,
      "demand_std": 15673.0,
      "unit_cost": 117.74,
      "margin_pct": 47.0,
      "pog_capacity": 41759.0
    },
    {
      "cluster_id": "CA_B_003",
      "segment": "B",
      "item_name": "Cat Supplies - B Item 3",
      "demand_mean": 63802.0,
      "demand_std": 12760.0,
      "unit_cost": 95.66,
      "margin_pct": 44.6,
      "pog_capacity": 27534.0
    },
    {
      "cluster_id": "CA_B_004",
      "segment": "B",
      "item_name": "Cat Supplies - B Item 4",
      "demand_mean": 71666.0,
      "demand_std": 14333.0,
      "unit_cost": 86.92,
      "margin_pct": 50.1,
      "pog_capacity": 36579.0
    },
    {
      "cluster_id": "CA_C_005",
      "segment": "C",
      "item_name": "Cat Supplies - C Item 5",
      "demand_mean": 33469.0,
      "demand_std": 10041.0,
      "unit_cost": 32.14,
      "margin_pct": 57.9,
      "pog_capacity": 19690.0
    },
    {
      "cluster_id": "CA_C_006",
      "segment": "C",
      "item_name": "Cat Supplies - C Item 6",
      "demand_mean": 25585.0,
      "demand_std": 7676.0,
      "unit_cost": 24.05,
      "margin_pct": 55.4,
      "pog_capacity": 12704.0
    },
    {
      "cluster_id": "CA_R_007",
      "segment": "R",
      "item_name": "Cat Supplies - R Item 7",
      "demand_mean": 32497.0,
      "demand_std": 3900.0,
      "unit_cost": 124.24,
      "margin_pct": 44.7,
      "pog_capacity": 13398.0
    },
    {
      "cluster_id": "CA_R_008",
      "segment": "R",
      "item_name": "Cat Supplies - R Item 8",
      "demand_mean": 29815.0,
      "demand_std": 3578.0,
      "unit_cost": 28.49,
      "margin_pct": 51.9,
      "pog_capacity": 11517.0
    }
  ],
  "total_demand_value": 41562386.0,
  "total_budget_needed": 46065666.0
}